[
  {
    "ID": "F1_1",
    "TEXT": "Nomina referente piano settoriale (1), Scenario ILO (2), Scenario IPE (2), Scenario ISI (2)"
  },
  {
    "ID": "F1_2",
    "TEXT": "Nomina referente piano settoriale"
  },
  {
    "ID": "F1_3",
    "TEXT": "Nomina referente piano settoriale"
  },
  {
    "ID": "F1_4",
    "TEXT": "Policy BCM, ruoli e responsabilità BCM"
  },
  {
    "ID": "F1_5",
    "TEXT": "Piano DR, Scenario ISI"
  },
  {
    "ID": "F1_6",
    "TEXT": "Piano DR, Scenario ISI"
  },
  {
    "ID": "F1_7",
    "TEXT": "Piano DR, Scenario ISI"
  },
  {
    "ID": "F1_8",
    "TEXT": "Piano DR, Scenario ISI"
  },
  {
    "ID": "F1_9",
    "TEXT": "Scenario ILO"
  },
  {
    "ID": "F1_10",
    "TEXT": "Scenario IPE"
  },
  {
    "ID": "F1_11",
    "TEXT": "Scenario ILO, Scenario IPE, Scenario ISI"
  },
  {
    "ID": "F1_12",
    "TEXT": "Scenario ILO, Scenario IPE, Scenario ISI"
  },
  {
    "ID": "F1_13",
    "TEXT": "Scenario Pandemia"
  },
  {
    "ID": "F1_14",
    "TEXT": "Piano DR, Scenario ISI"
  },
  {
    "ID": "F1_15",
    "TEXT": "Scenario ILO"
  },
  {
    "ID": "F1_16",
    "TEXT": "BIA"
  },
  {
    "ID": "F1_17",
    "TEXT": "Scenario ILO, Scenario IPE, Scenario ISI"
  },
  {
    "ID": "F1_18",
    "TEXT": "Scenario ILO, Scenario IPE, Scenario ISI"
  },
  {
    "ID": "F1_19",
    "TEXT": "Piano DR, Scenario ISI"
  },
  {
    "ID": "F1_20",
    "TEXT": "Piano DR, Scenario ISI"
  },
  {
    "ID": "F1_21",
    "TEXT": "Scenario ILO, Scenario ISI"
  },
  {
    "ID": "F1_24",
    "TEXT": "Piano DR, Scenario ISI"
  },
  {
    "ID": "F1_25",
    "TEXT": "Scenario ILO, Scenario IPE, Scenario ISI, Test BCM"
  },
  {
    "ID": "F1_26",
    "TEXT": "Scenario ILO, Scenario IPE, Scenario ISI, Test BCM"
  },
  {
    "ID": "F1_27",
    "TEXT": "Piano DR, Scenario ISI"
  },
  {
    "ID": "F1_28",
    "TEXT": "Controllo transazioni, Controllo conti, Frode, SCA, Pagamento, Autorizzazioni"
  },
  {
    "ID": "F1_29",
    "TEXT": "Controllo conti, Frode, SCA"
  },
  {
    "ID": "F1_30",
    "TEXT": "Controllo transazioni, Controllo conti, Frode, SCA, Pagamento"
  },
  {
    "ID": "F1_31",
    "TEXT": "Accesso al sistema, Controllo privilegi, Accesso al sistema, Gestione account"
  },
  {
    "ID": "F1_32",
    "TEXT": "Gestione account, Need to know"
  },
  {
    "ID": "F1_33",
    "TEXT": "Gestione account, Need to know, Need to use, Segregation of duties"
  },
  {
    "ID": "F1_34",
    "TEXT": "Logging, Gestione account"
  },
  {
    "ID": "F1_35",
    "TEXT": "Controllo privilegi, Accesso al sistema, Gestione account, Segregation of duties, Autorizzazioni"
  },
  {
    "ID": "F1_36",
    "TEXT": "Logging, Monitoraggio, Gestione account"
  },
  {
    "ID": "F1_37",
    "TEXT": "Logging"
  },
  {
    "ID": "F1_38",
    "TEXT": "Logging"
  },
  {
    "ID": "F1_39",
    "TEXT": "Logging"
  },
  {
    "ID": "F1_40",
    "TEXT": "Logging, Backup"
  },
  {
    "ID": "F1_41",
    "TEXT": "Controllo accessi, Logging"
  },
  {
    "ID": "F1_42",
    "TEXT": "Gestione account"
  },
  {
    "ID": "F1_43",
    "TEXT": "Policy BCM, ruoli e responsabilità BCM, Scenario ILO, Scenario IPE, Scenario ISI, Scenario Pandemia"
  },
  {
    "ID": "F1_44",
    "TEXT": "Controllo accessi, Gestione account, Accesso al sistema, Identificazione utenti"
  },
  {
    "ID": "F1_45",
    "TEXT": "Sicurezza dei sistemi, Audit"
  },
  {
    "ID": "F1_46",
    "TEXT": "Policy BCM, ruoli e responsabilità BCM, Scenario ILO, Scenario IPE, Scenario ISI, Scenario Pandemia"
  },
  {
    "ID": "F1_47",
    "TEXT": "Network, Gestione traffico"
  },
  {
    "ID": "F1_50",
    "TEXT": "Gestione account, Logging, Monitoraggio"
  },
  {
    "ID": "F1_51",
    "TEXT": "Gestione account, Controllo privilegi, Accesso al sistema"
  },
  {
    "ID": "F1_52",
    "TEXT": "Logging"
  },
  {
    "ID": "F1_53",
    "TEXT": "Gestione incidenti"
  },
  {
    "ID": "F1_54",
    "TEXT": "Gestione account, Logging, Monitoraggio"
  },
  {
    "ID": "F1_55",
    "TEXT": "Controllo transazioni, Frode, Pagamento"
  },
  {
    "ID": "F1_56",
    "TEXT": "Frode, Pagamento"
  },
  {
    "ID": "F1_57",
    "TEXT": "Frode, Pagamento"
  },
  {
    "ID": "F1_58",
    "TEXT": "Frode, Pagamento, Monitoraggio"
  },
  {
    "ID": "F1_59",
    "TEXT": "Frode"
  },
  {
    "ID": "F1_60",
    "TEXT": "Frode, Pagamento, Monitoraggio"
  },
  {
    "ID": "F1_61",
    "TEXT": "Frode"
  },
  {
    "ID": "F1_62",
    "TEXT": "Controllo accessi, Accesso al sistema"
  },
  {
    "ID": "F1_63",
    "TEXT": "Gestione account, Controllo privilegi, Need to know, Need to use, Segregation of duties, Controllo privilegi"
  },
  {
    "ID": "F1_64",
    "TEXT": "Policy sicurezza, Controllo accessi, Accesso al sistema, Gestione account, Autenticazione"
  },
  {
    "ID": "F1_65",
    "TEXT": "Formazione, Awareness"
  },
  {
    "ID": "F1_66",
    "TEXT": "Policy sicurezza, Formazione, Awareness, Policy BCM"
  },
  {
    "ID": "F1_67",
    "TEXT": "Flussi Sicurezza, Flussi BCM"
  },
  {
    "ID": "F1_68",
    "TEXT": "Accesso al sistema, Need to know, Need to use, Segregation of duties, Autorizzazioni"
  },
  {
    "ID": "F1_69",
    "TEXT": "Gestione account, Need to know, Need to use, Segregation of duties, Controllo privilegi"
  },
  {
    "ID": "F1_70",
    "TEXT": "Gestione account"
  },
  {
    "ID": "F1_71",
    "TEXT": "Gestione account, Need to know, Need to use, Segregation of duties, Controllo privilegi"
  },
  {
    "ID": "F1_72",
    "TEXT": "Gestione account, Monitoraggio"
  },
  {
    "ID": "F1_73",
    "TEXT": "Gestione account, Controllo privilegi, Need to know, Need to use, Segregation of duties, Accesso al sistema"
  },
  {
    "ID": "F1_74",
    "TEXT": "Accesso al sistema, Gestione sessioni"
  },
  {
    "ID": "F1_75",
    "TEXT": "Gestione account, Accesso al sistema"
  },
  {
    "ID": "F1_76",
    "TEXT": "Gestione account, Accesso al sistema"
  },
  {
    "ID": "F1_77",
    "TEXT": "Gestione account, Accesso al sistema"
  },
  {
    "ID": "F1_78",
    "TEXT": "Gestione account, Controllo privilegi, Need to know, Need to use, Segregation of duties"
  },
  {
    "ID": "F1_79",
    "TEXT": "Gestione sessioni, Accesso al sistema"
  },
  {
    "ID": "F1_80",
    "TEXT": "Gestione account"
  },
  {
    "ID": "F1_81",
    "TEXT": "Gestione account, Accesso al sistema"
  },
  {
    "ID": "F1_82",
    "TEXT": "Vulnerability assessment, Gestione vulnerabilità, Test di sicurezza, Controlli di sicurezza"
  },
  {
    "ID": "F1_83",
    "TEXT": "Penetration testing, Gestione vulnerabilità, Test di sicurezza, Controlli di sicurezza"
  },
  {
    "ID": "F1_84",
    "TEXT": "Threat intelligence, SOC, Data breach"
  },
  {
    "ID": "F1_85",
    "TEXT": "DLP, SOC, Data breach"
  },
  {
    "ID": "F1_86",
    "TEXT": "Controlli di sicurezza, Terze parti"
  },
  {
    "ID": "F1_87",
    "TEXT": "Terze parti, Contratti"
  },
  {
    "ID": "F1_88",
    "TEXT": "Terze parti, Gestione configurazioni, Patch management, Change"
  },
  {
    "ID": "F1_89",
    "TEXT": "Terze parti, Contratti, SCA, Accesso al sistema"
  },
  {
    "ID": "F1_90",
    "TEXT": "Terze parti, Contratti, Monitoraggio"
  },
  {
    "ID": "F1_91",
    "TEXT": "Cancellazione sicura, Accesso al sistema, Controllo accessi, Data breach, Endpoint"
  },
  {
    "ID": "F1_92",
    "TEXT": "Gestione configurazioni, Utilizzo sicuro, Gestione connessioni, Endpoint, Data breach, Hardening"
  },
  {
    "ID": "F1_93",
    "TEXT": "Gestione connessioni, Endpoint"
  },
  {
    "ID": "F1_94",
    "TEXT": "Endpoint, Cifratura, Data breach"
  },
  {
    "ID": "F1_95",
    "TEXT": "Controllo accessi, Logging"
  },
  {
    "ID": "F1_96",
    "TEXT": "Controlli di sicurezza, Autorizzazioni"
  },
  {
    "ID": "F1_97",
    "TEXT": "Identificazione servizi"
  },
  {
    "ID": "F1_98",
    "TEXT": "Identificazione servizi, Accesso al sistema"
  },
  {
    "ID": "F1_99",
    "TEXT": "Gestione connessioni, Cifratura, Controlli di sicurezza"
  },
  {
    "ID": "F1_100",
    "TEXT": "Gestione sessioni, Accesso al sistema"
  },
  {
    "ID": "F1_101",
    "TEXT": "Gestione configurazioni, Controlli di sicurezza, Hardening"
  },
  {
    "ID": "F1_102",
    "TEXT": "Crisis Management, Gestione incidenti"
  },
  {
    "ID": "F1_103",
    "TEXT": "Gestione connessioni, Gestione configurazioni"
  },
  {
    "ID": "F1_104",
    "TEXT": "Cifratura, Logging"
  },
  {
    "ID": "F1_105",
    "TEXT": "Controlli di sicurezza, Hardening, Autorizzazioni"
  },
  {
    "ID": "F1_106",
    "TEXT": "Scenario ILO, Scenario IPE, Scenario ISI, Piano DR, Terze parti, Policy BCM"
  },
  {
    "ID": "F1_107",
    "TEXT": "Scenario ILO, Scenario IPE, Scenario ISI, Piano DR, Terze parti, Policy BCM, Test BCM"
  },
  {
    "ID": "F1_108",
    "TEXT": "Test BCM, Test di sicurezza"
  },
  {
    "ID": "F1_109",
    "TEXT": "Formazione, Awareness, Policy BCM, Policy sicurezza"
  },
  {
    "ID": "F1_110",
    "TEXT": "Cifratura, Sicurezza fisica, Gestione connessioni"
  },
  {
    "ID": "F1_111",
    "TEXT": "Cifratura, Data breach, Hardening, Controlli di sicurezza"
  },
  {
    "ID": "F1_112",
    "TEXT": "Gestione password, Cifratura"
  },
  {
    "ID": "F1_113",
    "TEXT": "Gestione account, Autorizzazioni"
  },
  {
    "ID": "F1_114",
    "TEXT": "Gestione account"
  },
  {
    "ID": "F1_115",
    "TEXT": "Data breach"
  },
  {
    "ID": "F1_116",
    "TEXT": "Frode, Gestione account"
  },
  {
    "ID": "F1_117",
    "TEXT": "Gestione account, Terze parti"
  },
  {
    "ID": "F1_118",
    "TEXT": "Gestione account, Terze parti"
  },
  {
    "ID": "F1_119",
    "TEXT": "Gestione account"
  },
  {
    "ID": "F1_120",
    "TEXT": "Gestione account"
  },
  {
    "ID": "F1_121",
    "TEXT": "Sistema informativo, Architettura"
  },
  {
    "ID": "F1_122",
    "TEXT": "Test di sicurezza, Penetration testing, SDLC"
  },
  {
    "ID": "F1_123",
    "TEXT": "Accesso al sistema, Segregation of duties, Hardening, Sicurezza dei sistemi, Autorizzazioni, Controllo privilegi"
  },
  {
    "ID": "F1_124",
    "TEXT": "Gestione password, Accesso al sistema"
  },
  {
    "ID": "F1_125",
    "TEXT": "Gestione password, Accesso al sistema"
  },
  {
    "ID": "F1_126",
    "TEXT": "Accesso al sistema, Segregation of duties, Hardening, Sicurezza dei sistemi, Autorizzazioni, Controllo privilegi"
  },
  {
    "ID": "F1_127",
    "TEXT": "Logging"
  },
  {
    "ID": "F1_128",
    "TEXT": "Logging"
  },
  {
    "ID": "F1_129",
    "TEXT": "Logging, Audit"
  },
  {
    "ID": "F1_130",
    "TEXT": "Logging, Audit"
  },
  {
    "ID": "F1_131",
    "TEXT": "Logging, Backup"
  },
  {
    "ID": "F1_132",
    "TEXT": "Logging, Backup"
  },
  {
    "ID": "F1_133",
    "TEXT": "Logging, Accesso al sistema, Need to know"
  },
  {
    "ID": "F1_134",
    "TEXT": "Logging, Accesso al sistema, Need to know"
  },
  {
    "ID": "F1_135",
    "TEXT": "Accesso al sistema, Autenticazione"
  },
  {
    "ID": "F1_136",
    "TEXT": "Accesso al sistema, Autenticazione"
  },
  {
    "ID": "F1_137",
    "TEXT": "Accesso al sistema"
  },
  {
    "ID": "F1_138",
    "TEXT": "Accesso al sistema"
  },
  {
    "ID": "F1_139",
    "TEXT": "Gestione account, Accesso al sistema"
  },
  {
    "ID": "F1_140",
    "TEXT": "Gestione account, Accesso al sistema"
  },
  {
    "ID": "F1_141",
    "TEXT": "Gestione account, Accesso al sistema"
  },
  {
    "ID": "F1_142",
    "TEXT": "Gestione account, Accesso al sistema"
  },
  {
    "ID": "F1_143",
    "TEXT": "Hardening, Sicurezza dei sistemi, Sistema informativo, Architettura"
  },
  {
    "ID": "F1_144",
    "TEXT": "Sicurezza dei sistemi, Sistema informativo, Architettura"
  },
  {
    "ID": "F1_145",
    "TEXT": "Sicurezza dei sistemi, Sistema informativo, Architettura"
  },
  {
    "ID": "F1_146",
    "TEXT": "Sicurezza dei sistemi, Sistema informativo, Architettura"
  },
  {
    "ID": "F1_147",
    "TEXT": "Sicurezza dei sistemi, Sistema informativo, Architettura"
  },
  {
    "ID": "F1_148",
    "TEXT": "Sicurezza dei sistemi, Sistema informativo, Architettura"
  },
  {
    "ID": "F1_149",
    "TEXT": "Cifratura, Accesso al sistema, Sicurezza dei sistemi, Sistema informativo"
  },
  {
    "ID": "F1_150",
    "TEXT": "Cifratura, Accesso al sistema, Sicurezza dei sistemi, Sistema informativo"
  },
  {
    "ID": "F1_151",
    "TEXT": "Sicurezza dei sistemi, Audit, Need to know"
  },
  {
    "ID": "F1_152",
    "TEXT": "Sicurezza dei sistemi, Audit, Need to know"
  },
  {
    "ID": "F1_153",
    "TEXT": "Accesso al sistema, Sicurezza dei sistemi"
  },
  {
    "ID": "F1_154",
    "TEXT": "Accesso al sistema, Sicurezza dei sistemi"
  },
  {
    "ID": "F1_155",
    "TEXT": "Gestione password, Accesso al sistema"
  },
  {
    "ID": "F1_156",
    "TEXT": "Gestione password, Accesso al sistema"
  },
  {
    "ID": "F1_157",
    "TEXT": "Gestione password, Accesso al sistema"
  },
  {
    "ID": "F1_158",
    "TEXT": "Gestione incidenti"
  },
  {
    "ID": "F1_159",
    "TEXT": "Gestione password, Accesso al sistema"
  },
  {
    "ID": "F1_160",
    "TEXT": "Accesso al sistema, Sicurezza dei sistemi, Controlli di sicurezza"
  },
  {
    "ID": "F1_161",
    "TEXT": "Accesso al sistema, Sicurezza dei sistemi, Controlli di sicurezza"
  },
  {
    "ID": "F1_162",
    "TEXT": "Accesso al sistema, Sicurezza dei sistemi, Controlli di sicurezza, Frode"
  },
  {
    "ID": "F1_172",
    "TEXT": "Accesso al sistema, Sicurezza dei sistemi, Controlli di sicurezza, Gestione password"
  },
  {
    "ID": "F1_173",
    "TEXT": "Accesso al sistema, Sicurezza dei sistemi, Controlli di sicurezza, Gestione password"
  },
  {
    "ID": "F1_174",
    "TEXT": "Accesso al sistema, Sicurezza dei sistemi, Controlli di sicurezza, Gestione password"
  },
  {
    "ID": "F1_175",
    "TEXT": "Cifratura, Accesso al sistema, Sicurezza dei sistemi, Sistema informativo"
  },
  {
    "ID": "F1_176",
    "TEXT": "Accesso al sistema, Sicurezza dei sistemi, Controlli di sicurezza"
  },
  {
    "ID": "F1_177",
    "TEXT": "Accesso al sistema, Sicurezza dei sistemi, Hardening, Gestione account, Data breach, Sistema informativo"
  },
  {
    "ID": "F1_178",
    "TEXT": "Piano DR, Scenario ISI"
  },
  {
    "ID": "F1_179",
    "TEXT": "Flussi BCM, Scenario ILO, Scenario IPE, Scenario ISI"
  },
  {
    "ID": "F1_180",
    "TEXT": "Flussi BCM, Scenario ILO, Scenario IPE, Scenario ISI"
  },
  {
    "ID": "F1_181",
    "TEXT": "Controllo accessi, Accesso al sistema, Frode, Controllo conti, Pagamento, Controllo transazioni"
  },
  {
    "ID": "F1_182",
    "TEXT": "Terze parti, Contratti"
  },
  {
    "ID": "F1_183",
    "TEXT": "Terze parti, Contratti"
  },
  {
    "ID": "F1_184",
    "TEXT": "Terze parti, Contratti, Scenario ILO, Scenario IPE, Scenario ISI"
  },
  {
    "ID": "F1_185",
    "TEXT": "Controllo accessi, Accesso al sistema, Frode, Controllo conti, Pagamento, Controllo transazioni, Autenticazione"
  },
  {
    "ID": "F1_186",
    "TEXT": "Accesso al sistema, Autenticazione"
  },
  {
    "ID": "F1_187",
    "TEXT": "Accesso al sistema, SCA, Gestione accessi"
  },
  {
    "ID": "F1_188",
    "TEXT": "Accesso al sistema, Sicurezza dei sistemi, Controlli di sicurezza"
  },
  {
    "ID": "F1_189",
    "TEXT": "Gestione password, Accesso al sistema"
  },
  {
    "ID": "F1_190",
    "TEXT": "Gestione password, Accesso al sistema"
  },
  {
    "ID": "F1_191",
    "TEXT": "Accesso al sistema, Sicurezza dei sistemi, Controlli di sicurezza"
  },
  {
    "ID": "F1_192",
    "TEXT": "Accesso al sistema, Autenticazione"
  },
  {
    "ID": "F1_193",
    "TEXT": "Accesso al sistema, Sicurezza dei sistemi, Controlli di sicurezza"
  },
  {
    "ID": "F1_194",
    "TEXT": "Gestione account"
  }
]